py3utils/__init__.py
py3utils/datetimeutil.py
py3utils/shellutil.py
py3utils/urlutil.py
py3utils-0.1.dist-info/DESCRIPTION.rst
py3utils-0.1.dist-info/METADATA
py3utils-0.1.dist-info/RECORD
py3utils-0.1.dist-info/WHEEL
py3utils-0.1.dist-info/metadata.json
py3utils-0.1.dist-info/top_level.txt
