Metadata-Version: 2.0
Name: py3utils
Version: 0.1
Summary: Useful Python 3.5 utils
Home-page: https://github.com/hezhiming/py3utils
Author: hezhiming
Author-email: he.zhiming@foxmail.com
License: MIT
Platform: UNKNOWN
Classifier: Intended Audience :: Developers
Classifier: Natural Language :: English
Classifier: Programming Language :: Python
Classifier: Programming Language :: Python :: 3
Classifier: Programming Language :: Python :: 3.3
Classifier: Programming Language :: Python :: 3.4
Classifier: Programming Language :: Python :: 3.5
Classifier: Programming Language :: Python :: 3.6
Classifier: Programming Language :: Python :: Implementation :: CPython
Requires-Dist: python-dateutil (>=2.5.0)
